{"cameraMode":{"drawMode":0,"name":"Shaded","section":"Shading Mode"},"sceneLighting":true,"audioPlay":false,"sceneViewState":{"showFog":true,"showMaterialUpdate":false,"showSkybox":true,"showFlares":true,"showImageEffects":true,"showParticleSystems":true},"in2DMode":false,"pivot":{"x":24.3363037109375,"y":-7.931840896606445,"z":-4.294652938842773},"rotation":{"x":0.006980632431805134,"y":0.9356042146682739,"z":-0.3524949252605438,"w":0.018528277054429055},"size":36.68016052246094,"orthographic":false}